kth/__init__.py
kth/binary.py
kth/errors.py
kth/node.py
kth/p2p.py
kth/primitives.py
kth/requirements.txt
kth/result.py
kth/tools.py
kth/wallet.py
kth/chain/__init__.py
kth/chain/block.py
kth/chain/chain.py
kth/chain/genericList.py
kth/chain/header.py
kth/chain/input.py
kth/chain/inputList.py
kth/chain/objects.py
kth/chain/output.py
kth/chain/outputList.py
kth/chain/outputPoint.py
kth/chain/script.py
kth/chain/transaction.py
kth/chain/transactionList.py
kth/config/__init__.py
kth/config/blockchainSettings.py
kth/config/network.py
kth/config/settings.py
kth-0.8.0.dist-info/METADATA
kth-0.8.0.dist-info/WHEEL
kth-0.8.0.dist-info/top_level.txt
kth-0.8.0.dist-info/RECORD
